fid_helper_pytorch/__init__.py
fid_helper_pytorch/__version__.py
fid_helper_pytorch/_download_tool.py
fid_helper_pytorch/_load_default_model.py
fid_helper_pytorch/_resample_func.py
fid_helper_pytorch/cmd.py
fid_helper_pytorch/default_1.pt
fid_helper_pytorch/fid_helper_pytorch.py
fid_helper_pytorch-0.1.3.dist-info/LICENSE
fid_helper_pytorch-0.1.3.dist-info/METADATA
fid_helper_pytorch-0.1.3.dist-info/WHEEL
fid_helper_pytorch-0.1.3.dist-info/entry_points.txt
fid_helper_pytorch-0.1.3.dist-info/top_level.txt
fid_helper_pytorch-0.1.3.dist-info/RECORD
